{"entities": {"dummy": {"short": "dummy", "verbose": "dummy"}}, "relations": {"birth-place": {"short": "birth-place", "verbose": "birth-place", "symmetric": false}, "headquarters": {"short": "headquarters", "verbose": "headquarters", "symmetric": false}, "event-year": {"short": "event-year", "verbose": "event-year", "symmetric": false}, "has-population": {"short": "has-population", "verbose": "has-population", "symmetric": false}, "eats": {"short": "eats", "verbose": "eats", "symmetric": false}, "has-author": {"short": "has-author", "verbose": "has-author", "symmetric": false}, "has-genre": {"short": "has-genre", "verbose": "has-genre", "symmetric": false}, "has-length": {"short": "has-length", "verbose": "has-length", "symmetric": false}, "is-where": {"short": "is-where", "verbose": "is-where", "symmetric": false}, "invented-by": {"short": "invented-by", "verbose": "invented-by", "symmetric": false}, "starring": {"short": "starring", "verbose": "starring", "symmetric": false}, "first-product": {"short": "first-product", "verbose": "first-product", "symmetric": false}, "movie-has-director": {"short": "movie-has-director", "verbose": "movie-has-director", "symmetric": false}, "has-parent": {"short": "has-parent", "verbose": "has-parent", "symmetric": false}, "won-award": {"short": "won-award", "verbose": "won-award", "symmetric": false}, "org-has-founder": {"short": "org-has-founder", "verbose": "org-has-founder", "symmetric": false}, "has-type": {"short": "has-type", "verbose": "has-type", "symmetric": false}, "has-child": {"short": "has-child", "verbose": "has-child", "symmetric": false}, "has-lifespan": {"short": "has-lifespan", "verbose": "has-lifespan", "symmetric": false}, "has-weight": {"short": "has-weight", "verbose": "has-weight", "symmetric": false}, "has-highest-mountain": {"short": "has-highest-mountain", "verbose": "has-highest-mountain", "symmetric": false}, "has-nationality": {"short": "has-nationality", "verbose": "has-nationality", "symmetric": false}, "org-has-member": {"short": "org-has-member", "verbose": "org-has-member", "symmetric": false}, "has-tourist-attraction": {"short": "has-tourist-attraction", "verbose": "has-tourist-attraction", "symmetric": false}, "has-sibling": {"short": "has-sibling", "verbose": "has-sibling", "symmetric": false}, "is-member-of": {"short": "is-member-of", "verbose": "is-member-of", "symmetric": false}, "no_relation": {"short": "no_relation", "verbose": "no_relation", "symmetric": true}, "has-edu": {"short": "has-edu", "verbose": "has-edu", "symmetric": false}, "org-leader": {"short": "org-leader", "verbose": "org-leader", "symmetric": false}, "invented-when": {"short": "invented-when", "verbose": "invented-when", "symmetric": false}, "has-spouse": {"short": "has-spouse", "verbose": "has-spouse", "symmetric": false}, "post-code": {"short": "post-code", "verbose": "post-code", "symmetric": false}, "loc-leader": {"short": "loc-leader", "verbose": "loc-leader", "symmetric": false}, "has-height": {"short": "has-height", "verbose": "has-height", "symmetric": false}, "from-country": {"short": "from-country", "verbose": "from-country", "symmetric": false}, "has-occupation": {"short": "has-occupation", "verbose": "has-occupation", "symmetric": false}}}